defense_finder_viz/__init__.py
defense_finder_viz/systems_palette.csv
defense_finder_viz_cli/__init__.py
defense_finder_viz_cli/main.py
mdmparis_defense_finder_viz-0.0.7.dist-info/LICENSE
mdmparis_defense_finder_viz-0.0.7.dist-info/METADATA
mdmparis_defense_finder_viz-0.0.7.dist-info/WHEEL
mdmparis_defense_finder_viz-0.0.7.dist-info/entry_points.txt
mdmparis_defense_finder_viz-0.0.7.dist-info/top_level.txt
mdmparis_defense_finder_viz-0.0.7.dist-info/RECORD
