Metadata-Version: 2.1
Name: mdmparis-defense-finder-viz
Version: 0.0.7
Summary: A helper tool to format data for defense-finder-web visualization from Prodigal and Defense Finder outputs.
Home-page: https://github.com/mdmparis/defense-finder-viz
Author: Alexandre Hervé
Author-email: alexandreherve@protonmail.com
License: GPLv3
Platform: UNKNOWN
Classifier: Development Status :: 4 - Beta
Classifier: Environment :: Console
Classifier: Operating System :: POSIX
Classifier: Programming Language :: Python :: 3
Classifier: Programming Language :: Python :: 3.7
Classifier: Programming Language :: Python :: 3.8
Classifier: Programming Language :: Python :: 3.9
Classifier: License :: OSI Approved :: GNU General Public License v3 (GPLv3)
Classifier: Intended Audience :: Science/Research
Classifier: Topic :: Scientific/Engineering :: Bio-Informatics
Requires-Python: >=3.7
License-File: LICENSE
Requires-Dist: pandas (==1.3.2)
Requires-Dist: click (==8.0.3)
Requires-Dist: bio (==1.3.3)
Requires-Dist: seqio (==0.0.7)
